{
  "color": [
    {
      "name": "start_window_background",
      "value": "#121212"
    },
    {
      "name": "page_background",
      "value": "#FF121212"
    },
    {
      "name": "text_title",
      "value": "#FFFFFF"
    },
    {
      "name": "text_primary",
      "value": "#E0E0E0"
    },
    {
      "name": "text_secondary",
      "value": "#B0B0B0"
    },
    {
      "name": "text_hint",
      "value": "#707070"
    },
    {
      "name": "divider",
      "value": "#2A2A2A"
    },
    {
      "name": "homepage_menu_button_divider",
      "value": "#2A2A2A"
    },
    {
      "name": "icon_normal",
      "value": "#B0B0B0"
    },
    {
      "name": "icon_pressed",
      "value": "#e5FFFFFF"
    },
    {
      "name": "icon_highlight",
      "value": "#505050"
    },
    {
      "name": "tag_background",
      "value": "#2A2A2A"
    },
    {
      "name": "background_gray",
      "value": "#1E1E1E"
    },
    {
      "name": "dialog_background",
      "value": "#1E1E1E"
    },
    {
      "name": "homepage_menu_button_normal",
      "value": "#FF212121"
    },
    {
      "name": "homepage_menu_button_pressed",
      "value": "#454545"
    },
    {
      "name": "back_button_normal",
      "value": "#252525"
    },
    {
      "name": "setting_item_background",
      "value": "#FF2C2C2F"
    },
    {
      "name": "setting_button_normal",
      "value": "#E0E0E0"
    },
    {
      "name": "text_click",
      "value": "#64B5F6"
    },
    {
      "name": "skeleton_loading",
      "value": "#333333"
    },
    {
      "name": "success",
      "value": "#66BB6A"
    },
    {
      "name": "error",
      "value": "#EF5350"
    },
    {
      "name": "text_tertiary",
      "value": "#757575"
    },
    {
      "name": "card_active_bg",
      "value": "#2A2A2A"
    },
    {
      "name": "billing_flash_bg",
      "value": "#1E90FF1A"
    },
    {
      "name": "card_background",
      "value": "#FF121212"
    },
    {
      "name": "button_background",
      "value": "#2A2A2A"
    },
    {
      "name": "border_line",
      "value": "#80969696"
    },
    {
      "name": "card_background_two",
      "value": "#242424"
    },
    {
      "name": "title_emphasis_color",
      "value": "#fecc11"
    }
  ]
}